sql_judge_utils/__init__.py
sql_judge_utils/database.py
sql_judge_utils/mysql.py
sql_judge_utils/parser.py
sql_judge_utils/postgresql.py
sql_judge_utils/validator.py
sql_judge_utils-0.1.15.dist-info/METADATA
sql_judge_utils-0.1.15.dist-info/WHEEL
sql_judge_utils-0.1.15.dist-info/RECORD
