Metadata-Version: 2.3
Name: sql-judge-utils
Version: 0.1.15
Summary: Utilities for writing tests for Quera SQL judge.
Project-URL: Homepage, https://github.com/QueraTeam/sql-judge-utils
Author-email: Quera <info@quera.ir>
License: MIT
Classifier: Intended Audience :: Developers
Classifier: Operating System :: OS Independent
Classifier: Programming Language :: Python
Classifier: Programming Language :: Python :: 3.9
Requires-Python: >=3.9
Requires-Dist: mysql-connector-python>=8.0.25
Requires-Dist: psycopg2-binary>=2.9.1
